portfolio_toolkit/__init__.py
portfolio_toolkit/account/__init__.py
portfolio_toolkit/account/account.py
portfolio_toolkit/account/transaction.py
portfolio_toolkit/asset/__init__.py
portfolio_toolkit/asset/market/__init__.py
portfolio_toolkit/asset/market/market_asset.py
portfolio_toolkit/asset/market/market_asset_list.py
portfolio_toolkit/asset/optimization/__init__.py
portfolio_toolkit/asset/optimization/optimization_asset.py
portfolio_toolkit/asset/portfolio/__init__.py
portfolio_toolkit/asset/portfolio/asset_from_dict.py
portfolio_toolkit/asset/portfolio/portfolio_asset.py
portfolio_toolkit/asset/portfolio/portfolio_asset_transaction.py
portfolio_toolkit/cli/__init__.py
portfolio_toolkit/cli/cli.py
portfolio_toolkit/cli/main.py
portfolio_toolkit/cli/commands/__init__.py
portfolio_toolkit/cli/commands/clear_cache.py
portfolio_toolkit/cli/commands/utils.py
portfolio_toolkit/cli/commands/optimization/__init__.py
portfolio_toolkit/cli/commands/optimization/frontier.py
portfolio_toolkit/cli/commands/optimization/optimization.py
portfolio_toolkit/cli/commands/optimization/risk.py
portfolio_toolkit/cli/commands/portfolio/__init__.py
portfolio_toolkit/cli/commands/portfolio/dump_data_frame.py
portfolio_toolkit/cli/commands/portfolio/evolution.py
portfolio_toolkit/cli/commands/portfolio/performance.py
portfolio_toolkit/cli/commands/portfolio/portfolio.py
portfolio_toolkit/cli/commands/portfolio/positions.py
portfolio_toolkit/cli/commands/portfolio/tax_report.py
portfolio_toolkit/cli/commands/portfolio/transactions.py
portfolio_toolkit/cli/commands/ticker/__init__.py
portfolio_toolkit/cli/commands/ticker/beta.py
portfolio_toolkit/cli/commands/ticker/compare.py
portfolio_toolkit/cli/commands/ticker/correlation.py
portfolio_toolkit/cli/commands/ticker/evolution.py
portfolio_toolkit/cli/commands/ticker/export_data.py
portfolio_toolkit/cli/commands/ticker/info.py
portfolio_toolkit/cli/commands/ticker/returns.py
portfolio_toolkit/cli/commands/ticker/returns_distribution.py
portfolio_toolkit-0.2.0.dist-info/licenses/LICENSE
portfolio_toolkit-0.2.0.dist-info/METADATA
portfolio_toolkit-0.2.0.dist-info/WHEEL
portfolio_toolkit-0.2.0.dist-info/entry_points.txt
portfolio_toolkit-0.2.0.dist-info/top_level.txt
portfolio_toolkit-0.2.0.dist-info/RECORD
