Metadata-Version: 2.4
Name: portfolio-toolkit
Version: 0.2.0
Summary: A comprehensive toolkit for portfolio analysis and management
Author: Guido Genzone
License-Expression: MIT
Project-URL: Homepage, https://github.com/ggenzone/portfolio-tools
Project-URL: Documentation, https://ggenzone.github.io/portfolio-tools
Project-URL: Repository, https://github.com/ggenzone/portfolio-tools.git
Project-URL: Bug Tracker, https://github.com/ggenzone/portfolio-tools/issues
Keywords: portfolio,finance,investment,analysis,toolkit
Classifier: Development Status :: 4 - Beta
Classifier: Intended Audience :: Financial and Insurance Industry
Classifier: Operating System :: OS Independent
Classifier: Programming Language :: Python :: 3
Classifier: Programming Language :: Python :: 3.9
Classifier: Programming Language :: Python :: 3.10
Classifier: Programming Language :: Python :: 3.11
Classifier: Programming Language :: Python :: 3.12
Classifier: Topic :: Office/Business :: Financial :: Investment
Classifier: Topic :: Scientific/Engineering :: Information Analysis
Requires-Python: >=3.9
License-File: LICENSE
Requires-Dist: pandas>=2.0.0
Requires-Dist: numpy<2.0.0,>=1.24.0
Requires-Dist: scipy>=1.10.0
Requires-Dist: matplotlib>=3.7.0
Requires-Dist: yfinance>=0.2.0
Requires-Dist: tabulate
Requires-Dist: click>=8.0.0
Provides-Extra: dev
Requires-Dist: pytest>=7.0.0; extra == "dev"
Requires-Dist: black>=23.0.0; extra == "dev"
Requires-Dist: isort>=5.0.0; extra == "dev"
Requires-Dist: flake8>=6.0.0; extra == "dev"
Provides-Extra: docs
Requires-Dist: sphinx>=7.0.0; extra == "docs"
Requires-Dist: sphinx-rtd-theme>=1.3.0; extra == "docs"
Dynamic: license-file
